sgevalviz/__init__.py
sgevalviz/cli.py
sgevalviz/cli_test.py
sgevalviz/fill_data.py
sgevalviz/plot.py
sgevalviz/pre_process.py
sgevalviz/statistical_analysis.py
sgevalviz/utils.py
sgevalviz/configs/__init__.py
sgevalviz/configs/augustus.json
sgevalviz/configs/default.json
sgevalviz-0.2.0.dist-info/METADATA
sgevalviz-0.2.0.dist-info/WHEEL
sgevalviz-0.2.0.dist-info/entry_points.txt
sgevalviz-0.2.0.dist-info/top_level.txt
sgevalviz-0.2.0.dist-info/RECORD
