Metadata-Version: 2.4
Name: sgevalviz
Version: 0.2.0
Summary: An improved version of sgeval with visualization and statistical analysis tools for GTFS bioinformatics data.
Author: Vinícius Araújo
License: MIT
Project-URL: Homepage, https://github.com/AraujoVE/sgevalviz
Project-URL: Repository, https://github.com/AraujoVE/sgevalviz
Project-URL: Issues, https://github.com/AraujoVE/sgevalviz/issues
Requires-Python: >=3.10
Requires-Dist: pandas>=2.0
Requires-Dist: matplotlib>=3.7
Requires-Dist: numpy>=1.24
